mlc_db_models/__init__.py
mlc_db_models/base.py
mlc_db_models/organization.py
mlc_db_models/user.py
mlc_db_models-0.1.0.dist-info/METADATA
mlc_db_models-0.1.0.dist-info/WHEEL
mlc_db_models-0.1.0.dist-info/RECORD
