Metadata-Version: 2.4
Name: mlc-db-models
Version: 0.1.0
Requires-Dist: sqlalchemy
